osiris/Osiris.py
osiris/OsirisDB.py
osiris/OsirisPlugin.py
osiris/OsirisSystem.py
osiris/__init__.py
osiris/const.py
osiris/CLI/BackupCli.py
osiris/CLI/BackupExecutionCli.py
osiris/CLI/EnvironmentCli.py
osiris/CLI/ObjectCli.py
osiris/CLI/OsirisCli.py
osiris/CLI/SystemCli.py
osiris/CLI/__init__.py
osiris/plugins/openstack/def.json
osiris/plugins/openstack/objects/availabilityZone.json
osiris/plugins/openstack/objects/catalog.json
osiris/plugins/openstack/objects/endpoint.json
osiris/plugins/openstack/objects/flavor.json
osiris/plugins/openstack/objects/floatingIP.json
osiris/plugins/openstack/objects/host.json
osiris/plugins/openstack/objects/hypervisor.json
osiris/plugins/openstack/objects/image.json
osiris/plugins/openstack/objects/keypair.json
osiris/plugins/openstack/objects/network.json
osiris/plugins/openstack/objects/port.json
osiris/plugins/openstack/objects/project.json
osiris/plugins/openstack/objects/server.json
osiris/plugins/openstack/objects/subnet.json
osiris/plugins/openstack/objects/user.json
osiris/plugins/openstack/scripts/flavorIntrospect
osiris/plugins/openstack/scripts/privateNetworkCreate
osiris/plugins/openstack/scripts/privateNetworkDelete
osiris/plugins/openstack/scripts/scriptInit
osiris/plugins/openstack/scripts/secgroupRuleCreate
osiris/plugins/openstack/scripts/serverCreate
osiris/plugins/openstack/scripts/serverDelete
osiris/plugins/openstack/scripts/userIntrospect
osiris/plugins/openstack/scripts/volume-type-create
atos_osiris-0.0.6.dist-info/AUTHORS.md
atos_osiris-0.0.6.dist-info/LICENSE
atos_osiris-0.0.6.dist-info/METADATA
atos_osiris-0.0.6.dist-info/WHEEL
atos_osiris-0.0.6.dist-info/entry_points.txt
atos_osiris-0.0.6.dist-info/top_level.txt
atos_osiris-0.0.6.dist-info/zip-safe
atos_osiris-0.0.6.dist-info/RECORD
