Metadata-Version: 2.1
Name: atos-osiris
Version: 0.0.6
Summary: Perform generic actions on specific systems
Home-page: https://git.atosone.com/osiris/osiris/
Author: # Credits
